python_anopi/__init__.py
python_anopi-0.3.1.dist-info/LICENSE.txt
python_anopi-0.3.1.dist-info/METADATA
python_anopi-0.3.1.dist-info/WHEEL
python_anopi-0.3.1.dist-info/top_level.txt
python_anopi-0.3.1.dist-info/RECORD
