Metadata-Version: 2.1
Name: python_anopi
Version: 0.3.1
Home-page: https://github.com/AndreasScharf/python-anopi
Author: Andreas Scharf
Author-email: info@frappgmbh.de
License: MIT
License-File: LICENSE.txt
Requires-Dist: pi-ina219
